{
  "id": "the-next-5-years-of-supply-chain-security-on-pypi-59c51472",
  "title": "The Next 5 Years of Supply Chain Security on PyPI",
  "type": "presentation",
  "publicationDate": "2024",
  "authors": [
    "William Woodruff"
  ],
  "url": "presentations/The%20Next%205%20Years%20of%20Supply%20Chain%20Security%20on%20PyPI/",
  "categories": {
    "publicationType": "presentation",
    "domain": [
      "supply-chain",
      "ai-ml"
    ]
  },
  "tags": {
    "topics": [
      "supply-chain-security"
    ]
  }
}